fun_with_flags/__init__.py
fun_with_flags/api.py
fun_with_flags/auth.py
fun_with_flags/flags.py
hattrick_fun_with_flags-0.1.1.dist-info/METADATA
hattrick_fun_with_flags-0.1.1.dist-info/WHEEL
hattrick_fun_with_flags-0.1.1.dist-info/licenses/LICENSE
hattrick_fun_with_flags-0.1.1.dist-info/RECORD
