Metadata-Version: 2.1
Name: hattrick_fun_with_flags
Version: 0.1.1
Summary: Add your description here
License-File: LICENSE
Requires-Python: >=3.8
Requires-Dist: flask>=3.0.0
Requires-Dist: hattrick-libs==0.5.1
